jvig/__init__.py
jvig/__main__.py
jvig/__version__.py
jvig/cli.py
jvig/gtfs.py
jvig/py.typed
jvig/util.py
jvig/valid.py
jvig/static/cal.js
jvig/static/jvig.png
jvig/static/style.css
jvig/tables/__init__.py
jvig/tables/agency.py
jvig/tables/calendar.py
jvig/tables/calendar_dates.py
jvig/tables/frequencies.py
jvig/tables/routes.py
jvig/tables/stops.py
jvig/tables/times.py
jvig/tables/trips.py
jvig/templates/agency.html.jinja
jvig/templates/calendar.html.jinja
jvig/templates/calendars.html.jinja
jvig/templates/routes.html.jinja
jvig/templates/stop.html.jinja
jvig/templates/stops.html.jinja
jvig/templates/trip.html.jinja
jvig/templates/trips.html.jinja
jvig-1.2.0.dist-info/METADATA
jvig-1.2.0.dist-info/WHEEL
jvig-1.2.0.dist-info/entry_points.txt
jvig-1.2.0.dist-info/top_level.txt
jvig-1.2.0.dist-info/RECORD
