Metadata-Version: 2.4
Name: jvig
Version: 1.2.0
Summary: GTFS Viewer written using Flask
License-Expression: GPL-3.0-or-later
Requires-Python: >=3.10
Requires-Dist: flask
Requires-Dist: markupsafe
